pysrcor/__init__.py
pysrcor/pysrcor.py
pysrcor-1.0.dist-info/LICENSE
pysrcor-1.0.dist-info/METADATA
pysrcor-1.0.dist-info/WHEEL
pysrcor-1.0.dist-info/top_level.txt
pysrcor-1.0.dist-info/RECORD
