Metadata-Version: 2.1
Name: pysrcor
Version: 1.0
Summary: A quick and easy function to correlate source positions from two catalogs
Home-page: https://github.com/Guang91/pysrcor/
Author: Guang Yang
Author-email: gyang206265@gmail.com
License: UNKNOWN
Platform: UNKNOWN
Classifier: Programming Language :: Python :: 3.7
Classifier: License :: OSI Approved :: MIT License
Requires-Dist: astropy
Requires-Dist: numpy
